grndctl/__init__.py
grndctl/main.py
grndctl-1.0.1.dist-info/LICENSE
grndctl-1.0.1.dist-info/METADATA
grndctl-1.0.1.dist-info/WHEEL
grndctl-1.0.1.dist-info/entry_points.txt
grndctl-1.0.1.dist-info/RECORD
